{
    "app_id": "d2add69c0b808781ddb8cac79139",
    "collection_id": "d4add69c0bb0a9e6adae9f95d87a",
    "items": [],
    "name": "Vending_Machine",
    "permissions": {},
    "schema": [
        {
            "ColumnName": "item_id",
            "ColumnType": "uuid",
            "PK": true
        },
        {
            "ColumnName": "vending_machine_id",
            "ColumnType": "int",
            "PK": false
        },
        {
            "ColumnName": "slot",
            "ColumnType": "int",
            "PK": false
        },
        {
            "ColumnName": "product_id",
            "ColumnType": "string",
            "PK": false
        },
        {
            "ColumnName": "quantity",
            "ColumnType": "int",
            "PK": false
        }
    ]
}